loggery/__init__.py
loggery/py.typed
loggery-0.7.2.dist-info/LICENSE
loggery-0.7.2.dist-info/METADATA
loggery-0.7.2.dist-info/WHEEL
loggery-0.7.2.dist-info/RECORD
