Metadata-Version: 2.3
Name: loggery
Version: 0.7.2
Summary: Configure logging with reduced noise from spammy modules with easy argparse support
License: LGPL-3.0-or-later
Author: Erskin Cherry
Author-email: erskin@eldritch.org
Requires-Python: >=3.11
Classifier: Programming Language :: Python :: 3
Classifier: Operating System :: OS Independent
Classifier: Intended Audience :: Developers
Classifier: License :: OSI Approved :: GNU Lesser General Public License v3 or later (LGPLv3+)
Classifier: Topic :: System :: Logging
Classifier: Development Status :: 4 - Beta
Project-URL: Homepage, https://gitlab.com/frobnic8/loggery
Project-URL: Repository, https://gitlab.com/frobnic8/loggery
